<?xml version="1.0" encoding="UTF-8"?>
<objects serializationModel="Studio.01.10.00">
    <object class="AudioFile" id="{4512ccdf-c9cb-401d-8e74-937558724cfa}">
        <property name="assetPath">
            <value>Vegetation_nr2_4 -  - Output - Stereo Out.wav</value>
        </property>
        <property name="frequencyInKHz">
            <value>48</value>
        </property>
        <property name="channelCount">
            <value>2</value>
        </property>
        <property name="length">
            <value>1.0526249999999999</value>
        </property>
        <relationship name="masterAssetFolder">
            <destination>{84071cf8-0f5b-4469-95e3-733423c59a8f}</destination>
        </relationship>
    </object>
</objects>
